AUTHORS.rst
CONTRIBUTING.rst
HISTORY.rst
LICENSE
MANIFEST.in
README.rst
setup.cfg
setup.py
docs/Makefile
docs/authors.rst
docs/conf.py
docs/contributing.rst
docs/history.rst
docs/index.rst
docs/installation.rst
docs/make.bat
docs/readme.rst
docs/usage.rst
profilelambda/__init__.py
profilelambda/profilelambda.py
profilelambda.egg-info/PKG-INFO
profilelambda.egg-info/SOURCES.txt
profilelambda.egg-info/dependency_links.txt
profilelambda.egg-info/not-zip-safe
profilelambda.egg-info/requires.txt
profilelambda.egg-info/top_level.txt
tests/test_profilelambda.py