Metadata-Version: 1.1
Name: profilelambda
Version: 0.3.0
Summary: Decorators and utils for profiling / debugging functions - especially AWS lambda
Home-page: https://github.com/hvnsweeting/profilelambda
Author: Viet Hung Nguyen
Author-email: hvn@familug.org
License: MIT license
Keywords: profilelambda
Platform: UNKNOWN
Classifier: Development Status :: 2 - Pre-Alpha
Classifier: Intended Audience :: Developers
Classifier: License :: OSI Approved :: MIT License
Classifier: Natural Language :: English
Classifier: Programming Language :: Python :: 2
Classifier: Programming Language :: Python :: 2.7
Classifier: Programming Language :: Python :: 3
Classifier: Programming Language :: Python :: 3.4
Classifier: Programming Language :: Python :: 3.5
Classifier: Programming Language :: Python :: 3.6
